tegstats/__init__.py
tegstats/teg_RMA_funcs.py
tegstats/teg_regression_funcs.py
tegstats-0.0.5.dist-info/LICENSE
tegstats-0.0.5.dist-info/METADATA
tegstats-0.0.5.dist-info/WHEEL
tegstats-0.0.5.dist-info/top_level.txt
tegstats-0.0.5.dist-info/RECORD
