Metadata-Version: 2.1
Name: tegstats
Version: 0.0.5
Summary: Multiple and hierarchical regression and repeated measures ANOVA
Home-page: https://github.com/thomasgladwin/teg_RMA
Author: Thomas E Gladwin
Author-email: thomasgladwin@hotmail.com
License: UNKNOWN
Platform: UNKNOWN
Classifier: Programming Language :: Python :: 3
Classifier: License :: OSI Approved :: MIT License
Classifier: Operating System :: OS Independent
Requires-Python: >=3.6
